view_logger
