Metadata-Version: 2.1
Name: view-logger
Version: 1.0
Summary: Package with decorators for views
Home-page: https://github.com/J4CKVVH173/view-logger
Author: J4CK VVH173, Polosha
Author-email: i78901234567890@gmail.com
License: UNKNOWN
Platform: UNKNOWN
Classifier: Programming Language :: Python :: 3
Classifier: License :: OSI Approved :: MIT License
Classifier: Operating System :: Unix
Classifier: Operating System :: Microsoft :: Windows
Classifier: Framework :: Django
Requires-Python: >=3.6
